{
    "label": "Restrições de acesso rodoviário",
    "source": {
        "type": "vector",
        "layer": "moztrsroads",
        "url": "mapbox://ona.3mipwbxa"
      },
    "type": "line",
    "layout": {
      "line-cap": "round",
      "line-join": "round"
    },
    "paint": {
      "line-color": {
        "property": "status",
        "type": "categorical",
        "stops": [
          ["Open", "#2ECC40"],
          ["Restricted", "#FF851B"],
          ["Closed", "#FF4136"]]
      },
      "line-width": 3,
      "line-opacity": 0.8
    },
    "popup": {
      "body": "<p style=text-align:left;> Status: {{status}} <br/></p>"
    },
    "credit": "HDX - hotosm_moz_roads"
  }