{
  "label": "Flood Extent in Tete and Zambezia Provinces - April 7",
  "source": {
    "type": "vector",
    "layer": "Flood_Extent_Tete_Zambezia_Pr-9n7snw",
    "url": "mapbox://ona.8j4so6tu"
  },
  "type": "fill",
  "layout": {
    "line-cap": "round",
    "line-join": "round"
  },
  "paint": {
    "fill-color": "#85144b",
    "fill-opacity": 0.6,
    "fill-outline-color": "#FF851B"
  },
  "menu-credit": "HDX - UNOSAT",
  "credit": "<a href=https://data.humdata.org/dataset/unosat-analysis-on-floods-in-mozambique-march-2019 target=_blank data-credit=credit>HDX - UNOSAT</a>"
}