{
    "label": "Distribuição Alimentar Cumulativa",
    "source": {
      "type": "vector",
      "layer": "mozambique_districts_final",
      "url": "mapbox://ona.9zeb0vb0",
      "data": "https://raw.githubusercontent.com/onaio/cycloneidai-2019-data/master/moz/cumulative-distribution/cumulative_distribution.csv",
      "minzoom": 2,
      "join": [
        "Distrito",
        "district"
      ]
    },
    "type": "fill",
    "property": "families",
    "categories": {
        "breaks": "yes",
        "color": "Blues",
        "vector-prop": "Distrito",
        "clusters": 7
      },
    "aggregate": {
        "type": "sum",
        "group-by": "district",
        "date-by": "end_date_of_distribution",
        "timeseries": {
            "field": "period"
        },
        "extraProps": [
            "families",
            "district",
            "people",
            "end_date_of_distribution",
            "children_under_5"
        ]
    },
    "popup": {
        "join": [
            "district",
            "Distrito"
        ],
        "header": "district",
        "body": "<p style=text-align:left;> <b>Famílias:</b> {{families}} <br> <b>Pessoas:</b> {{people}} <br> <b>Crianças menores de 5 anos:</b> {{children_under_5}} <br> <span style=float:right;>"
    },
    "visible": false,
    "menu-credit": "WFP",
    "credit": "<a href=https://drive.google.com/open?id=1CsISuvOTl5TLHXSHRHBjLpae7ZQnVrNR target=_blank data-credit=credit>WFP</a>",
    "category": "Cumulative Distribution"
  }